moppi/__init__.py
moppi/config.py
moppi/dependency.py
moppi/installer.py
moppi-0.4.0.dist-info/METADATA
moppi-0.4.0.dist-info/WHEEL
moppi-0.4.0.dist-info/entry_points.txt
moppi-0.4.0.dist-info/licenses/LICENSE
moppi-0.4.0.dist-info/RECORD
