Metadata-Version: 2.1
Name: moppi
Version: 0.4.0
Summary: Modern Python Package Installer
Project-URL: Homepage, https://github.com/lemanyk/moppi
Project-URL: Bug Tracker, https://github.com/lemanyk/moppi/issues
Author-email: Gennadii Egorov <lemanyk@gmail.com>
License-File: LICENSE
Classifier: License :: OSI Approved :: MIT License
Classifier: Operating System :: OS Independent
Classifier: Programming Language :: Python :: 3
Requires-Python: >=3.11
Requires-Dist: pyyaml==6.0
Requires-Dist: tomli-w==1.0.0
Provides-Extra: dev
Requires-Dist: build==0.9.0; extra == 'dev'
Requires-Dist: twine==4.0.2; extra == 'dev'
